pyhml/__init__.py
pyhml/pyhml.py
pyhml/util.py
pyhml/data/hml-0.9.4.xsd
pyhml/data/hml-0.9.5.xsd
pyhml/data/hml-0.9.6.xsd
pyhml/data/hml-0.9.7.xsd
pyhml/data/hml-1.0.1.xsd
pyhml/data/hml-1.0.2.xsd
pyhml/data/hml-1.0.xsd
pyhml/models/__init__.py
pyhml/models/allele_assignment.py
pyhml/models/base_model_.py
pyhml/models/consensus.py
pyhml/models/consensus_seq_block.py
pyhml/models/haploid.py
pyhml/models/hml.py
pyhml/models/ref_database.py
pyhml/models/ref_sequence.py
pyhml/models/reporting_center.py
pyhml/models/sample.py
pyhml/models/sbt_ngs.py
pyhml/models/seq_quality.py
pyhml/models/typing.py
pyhml/models/typing_method.py
pyhml/models/variant.py
pyhml/models/variant_effect.py
pyhml-0.0.5.dist-info/METADATA
pyhml-0.0.5.dist-info/RECORD
pyhml-0.0.5.dist-info/WHEEL
pyhml-0.0.5.dist-info/top_level.txt
