Metadata-Version: 2.1
Name: pyhml
Version: 0.0.5
Summary: Python HML parser
Home-page: https://github.com/nmdp-bioinformatics/pyHML
Author: Mike Halagan
Author-email: mhalagan@nmdp.org
License: LGPL 3.0
Keywords: pyhml
Platform: UNKNOWN
Classifier: Development Status :: 2 - Pre-Alpha
Classifier: Intended Audience :: Developers
Classifier: License :: OSI Approved :: GNU Lesser General Public License v3 (LGPLv3)
Classifier: Natural Language :: English
Classifier: Programming Language :: Python :: 3.6
Requires-Dist: biopython (==1.71)
Requires-Dist: pandas (==0.20.3)
Requires-Dist: numpy (==1.14.2)
Requires-Dist: six (==1.11.0)
Requires-Dist: xmlschema (==0.9.13)
Requires-Dist: xmltodict (==0.11.0)
Requires-Dist: pytz (==2018.3)
Requires-Dist: sh (==1.12.14)
Requires-Dist: python-dateutil (==2.7.2)
